.cvsignore
EXTERNALS.txt
README.txt
buildout.cfg
paster.cfg
setup.py
bootstrap/bootstrap.py
z3c/__init__.py
z3c.recipe.egg.egg-info/PKG-INFO
z3c.recipe.egg.egg-info/SOURCES.txt
z3c.recipe.egg.egg-info/dependency_links.txt
z3c.recipe.egg.egg-info/entry_points.txt
z3c.recipe.egg.egg-info/namespace_packages.txt
z3c.recipe.egg.egg-info/requires.txt
z3c.recipe.egg.egg-info/top_level.txt
z3c.recipe.egg.egg-info/zip-safe
z3c/recipe/__init__.py
z3c/recipe/egg/__init__.py
z3c/recipe/egg/editable.txt
z3c/recipe/egg/setup.txt
z3c/recipe/egg/tests/__init__.py
z3c/recipe/egg/tests/tests.py
z3c/recipe/egg/tests/bar/README.txt
z3c/recipe/egg/tests/bar/setup.py
z3c/recipe/egg/tests/bar/bar/__init__.py
z3c/recipe/egg/tests/foo/README.txt
z3c/recipe/egg/tests/foo/setup.py
z3c/recipe/egg/tests/foo/foo/__init__.py