Metadata-Version: 1.0
Name: z3c.recipe.egg
Version: 0.2
Summary: Recipies based on zc.recipe.egg for working with source distributions.
Home-page: http://cheeseshop.python.org/pypi/z3c.recipe.egg
Author: Ross Patterson
Author-email: me@rpatterson.net
License: GPL
Platform: UNKNOWN
Classifier: Framework :: Plone
Classifier: Framework :: Zope2
Classifier: Framework :: Zope3
Classifier: Programming Language :: Python
Classifier: Topic :: Software Development :: Libraries :: Python Modules
